hatch_webassets/__init__.py
hatch_webassets/_version.py
hatch_webassets/config.py
hatch_webassets/hooks.py
hatch_webassets/plugin.py
hatch_webassets/py.typed
hatch_webassets-0.1.0.dist-info/METADATA
hatch_webassets-0.1.0.dist-info/WHEEL
hatch_webassets-0.1.0.dist-info/entry_points.txt
hatch_webassets-0.1.0.dist-info/licenses/LICENSE
hatch_webassets-0.1.0.dist-info/RECORD
