Metadata-Version: 2.4
Name: hatch_webassets
Version: 0.1.0
Summary: A hatch build-hook for webassets
Project-URL: changelog, https://github.com/hasansezertasan/hatch_webassets/blob/main/CHANGELOG.md
Project-URL: documentation, https://github.com/hasansezertasan/hatch_webassets#readme
Project-URL: homepage, https://github.com/hasansezertasan/hatch_webassets
Project-URL: issues, https://github.com/hasansezertasan/hatch_webassets/issues
Project-URL: releasenotes, https://github.com/hasansezertasan/hatch_webassets/releases
Project-URL: source, https://github.com/hasansezertasan/hatch_webassets.git
Author-email: Hasan Sezer Taşan <hasansezertasan@gmail.com>
Maintainer-email: Hasan Sezer Taşan <hasansezertasan@gmail.com>
License-Expression: MIT
License-File: LICENSE
Keywords: build-hook,hatch,metadata,package,pypi,python,webassets
Classifier: Development Status :: 1 - Planning
Classifier: Framework :: Hatch
Classifier: Intended Audience :: Developers
Classifier: License :: OSI Approved :: MIT License
Classifier: Operating System :: OS Independent
Classifier: Programming Language :: Python
Classifier: Programming Language :: Python :: 3
Classifier: Programming Language :: Python :: 3 :: Only
Classifier: Programming Language :: Python :: 3.8
Classifier: Programming Language :: Python :: 3.9
Classifier: Programming Language :: Python :: 3.10
Classifier: Programming Language :: Python :: 3.11
Classifier: Programming Language :: Python :: 3.12
Classifier: Programming Language :: Python :: 3.13
Classifier: Programming Language :: Python :: 3.14
Classifier: Programming Language :: Python :: Implementation :: CPython
Classifier: Programming Language :: Python :: Implementation :: PyPy
Classifier: Topic :: Software Development
Classifier: Topic :: Software Development :: Libraries
Classifier: Topic :: Software Development :: Libraries :: Python Modules
Classifier: Typing :: Typed
Requires-Python: >=3.8
Requires-Dist: hatchling>=1.0.0
Requires-Dist: webassets>=2.0
